{
  "name": "warehouse/thumbnails/663_400x400.jpeg",
  "bucket": "bottleshop-3-veze-dev-54908.appspot.com",
  "metageneration": 1,
  "generation": 1652036851885,
  "contentType": "image/jpeg",
  "storageClass": "STANDARD",
  "contentDisposition": "inline",
  "cacheControl": "public, max-age=3600",
  "contentEncoding": "identity",
  "downloadTokens": [
    "67e06cf9-62e4-4a38-950a-ae9bcc47cbb8"
  ],
  "etag": "1NF24LHOz3tSf2RnKZrHSxXs8JY",
  "timeCreated": "2022-05-08T19:07:31.884Z",
  "updated": "2022-05-08T19:07:31.884Z",
  "size": 38651,
  "md5Hash": "jOlsXg8Z64+yJtlFTj5vCw==",
  "crc32c": "3162575551"
}