{
  "name": "flags/tm.svg",
  "bucket": "bottleshop-3-veze-dev-54908.appspot.com",
  "metageneration": 1,
  "generation": 1652036795527,
  "contentType": "image/svg+xml",
  "storageClass": "STANDARD",
  "contentDisposition": "inline",
  "cacheControl": "public, max-age=3600",
  "contentEncoding": "identity",
  "downloadTokens": [
    "309d28ae-4e20-4e66-86c3-e61533d7b2e6"
  ],
  "etag": "txzu1vtV9MdHphrAYKFGc4V1DdM",
  "timeCreated": "2022-05-08T19:06:35.526Z",
  "updated": "2022-05-08T19:06:35.527Z",
  "size": 42244,
  "md5Hash": "tfZSlgpPTLtMYw1Nqt/erA==",
  "crc32c": "1266449976"
}