{
  "name": "flags/az.svg",
  "bucket": "bottleshop-3-veze-dev-54908.appspot.com",
  "metageneration": 1,
  "generation": 1652036795512,
  "contentType": "image/svg+xml",
  "storageClass": "STANDARD",
  "contentDisposition": "inline",
  "cacheControl": "public, max-age=3600",
  "contentEncoding": "identity",
  "downloadTokens": [
    "a15fb121-a450-4505-8509-ab25f9478233"
  ],
  "etag": "SPf8ob5CFJEWAS4ywDd7AivEvdI",
  "timeCreated": "2022-05-08T19:06:35.511Z",
  "updated": "2022-05-08T19:06:35.511Z",
  "size": 524,
  "md5Hash": "sC4diX3Itp12ueEaUCi84w==",
  "crc32c": "2918852344"
}