{
  "name": "flags/fk.svg",
  "bucket": "bottleshop-3-veze-dev-54908.appspot.com",
  "metageneration": 1,
  "generation": 1652036795672,
  "contentType": "image/svg+xml",
  "storageClass": "STANDARD",
  "contentDisposition": "inline",
  "cacheControl": "public, max-age=3600",
  "contentEncoding": "identity",
  "downloadTokens": [
    "36b85f9e-1179-40ac-b865-597c7657c720"
  ],
  "etag": "qQFuolDe8V/PiXiut8RziEkC9Gk",
  "timeCreated": "2022-05-08T19:06:35.671Z",
  "updated": "2022-05-08T19:06:35.672Z",
  "size": 103295,
  "md5Hash": "TpUmqG1QLheA5LYjKdeTGg==",
  "crc32c": "3887003456"
}