{
  "name": "warehouse/0235.jpeg",
  "bucket": "bottleshop-3-veze-dev-54908.appspot.com",
  "metageneration": 1,
  "generation": 1652036862338,
  "contentType": "image/jpeg",
  "storageClass": "STANDARD",
  "contentDisposition": "inline",
  "cacheControl": "public, max-age=3600",
  "contentEncoding": "identity",
  "downloadTokens": [
    "62360654-a49e-4b00-9ea9-f316b0f0f764"
  ],
  "etag": "nhRBvNYqJpoKirl0b4rl4uw4/hA",
  "timeCreated": "2022-05-08T19:07:42.337Z",
  "updated": "2022-05-08T19:07:42.339Z",
  "size": 249299,
  "md5Hash": "9eKDycb3oLKCPjtvoNXecg==",
  "crc32c": "297181088"
}