{
  "name": "flags/cz.svg",
  "bucket": "bottleshop-3-veze-dev-54908.appspot.com",
  "metageneration": 1,
  "generation": 1652036795373,
  "contentType": "image/svg+xml",
  "storageClass": "STANDARD",
  "contentDisposition": "inline",
  "cacheControl": "public, max-age=3600",
  "contentEncoding": "identity",
  "downloadTokens": [
    "cb1abaf8-bc06-408b-960a-d1724a3a06a2"
  ],
  "etag": "xU10oJPo8zZb04PJnw7oJ919ubY",
  "timeCreated": "2022-05-08T19:06:35.372Z",
  "updated": "2022-05-08T19:06:35.372Z",
  "size": 212,
  "md5Hash": "BH5zLezWK50841CizY9N5g==",
  "crc32c": "149074398"
}