{
  "name": "warehouse/thumbnails/636_400x400.jpeg",
  "bucket": "bottleshop-3-veze-dev-54908.appspot.com",
  "metageneration": 1,
  "generation": 1652036851888,
  "contentType": "image/jpeg",
  "storageClass": "STANDARD",
  "contentDisposition": "inline",
  "cacheControl": "public, max-age=3600",
  "contentEncoding": "identity",
  "downloadTokens": [
    "3a1bd941-458f-4ffa-a43b-ab8c30140903"
  ],
  "etag": "oIPjxswKYIppRf1RRYRg6Ob/oY4",
  "timeCreated": "2022-05-08T19:07:31.887Z",
  "updated": "2022-05-08T19:07:31.887Z",
  "size": 35664,
  "md5Hash": "qzJCOxlN/LSs1Lm1xI+/Ig==",
  "crc32c": "974532724"
}