{
  "name": "flags/gw.svg",
  "bucket": "bottleshop-3-veze-dev-54908.appspot.com",
  "metageneration": 1,
  "generation": 1652036795089,
  "contentType": "image/svg+xml",
  "storageClass": "STANDARD",
  "contentDisposition": "inline",
  "cacheControl": "public, max-age=3600",
  "contentEncoding": "identity",
  "downloadTokens": [
    "b39db116-3007-415c-8962-220d3d662273"
  ],
  "etag": "YeJ+i0VRbdtLAOEES7aalAtYfm0",
  "timeCreated": "2022-05-08T19:06:35.089Z",
  "updated": "2022-05-08T19:06:35.089Z",
  "size": 602,
  "md5Hash": "UM7H/eDW50Ft2ONgLAsWJA==",
  "crc32c": "3517030465"
}