{
  "name": "flags/dj.svg",
  "bucket": "bottleshop-3-veze-dev-54908.appspot.com",
  "metageneration": 1,
  "generation": 1652036795174,
  "contentType": "image/svg+xml",
  "storageClass": "STANDARD",
  "contentDisposition": "inline",
  "cacheControl": "public, max-age=3600",
  "contentEncoding": "identity",
  "downloadTokens": [
    "09e01132-d01d-4e61-a8fb-3b5bce62383a"
  ],
  "etag": "mvCD7d47cTZ7U+2OqoAxa7a9ZfM",
  "timeCreated": "2022-05-08T19:06:35.173Z",
  "updated": "2022-05-08T19:06:35.173Z",
  "size": 322,
  "md5Hash": "AudeILKNcXvKFwNnAhr9cg==",
  "crc32c": "250105647"
}