{
  "name": "flags/me.svg",
  "bucket": "bottleshop-3-veze-dev-54908.appspot.com",
  "metageneration": 1,
  "generation": 1652036795428,
  "contentType": "image/svg+xml",
  "storageClass": "STANDARD",
  "contentDisposition": "inline",
  "cacheControl": "public, max-age=3600",
  "contentEncoding": "identity",
  "downloadTokens": [
    "6e6e7b20-2cdd-485b-82ea-2dc23e639b8a"
  ],
  "etag": "KHi+QUxsLR7MHEXYBctGXYbD4No",
  "timeCreated": "2022-05-08T19:06:35.427Z",
  "updated": "2022-05-08T19:06:35.427Z",
  "size": 59599,
  "md5Hash": "rXr9EvxO8hh2BMUwsGKtrA==",
  "crc32c": "1968759754"
}